[
{
  "model": "item.locale",
  "pk": 1,
  "fields": {
    "locale_name": "all"
  }
},
{
  "model": "item.locale",
  "pk": 2,
  "fields": {
    "locale_name": "ja"
  }
},
{
  "model": "item.locale",
  "pk": 3,
  "fields": {
    "locale_name": "en"
  }
},
{
  "model": "item.locale",
  "pk": 4,
  "fields": {
    "locale_name": "ko"
  }
},
{
  "model": "item.album",
  "pk": 1,
  "fields": {
    "album_title": "Please Please Me (1963.3)",
    "locales": [
      2,
      3
    ]
  }
},
{
  "model": "item.album",
  "pk": 2,
  "fields": {
    "album_title": "With The Beatles (1963.11)",
    "locales": [
      2,
      3
    ]
  }
},
{
  "model": "item.album",
  "pk": 3,
  "fields": {
    "album_title": "A Hard Day's Night (1964.7), Beatles for Sale (1964.12)",
    "locales": [
      3,
      4
    ]
  }
},
{
  "model": "item.album",
  "pk": 4,
  "fields": {
    "album_title": "Help! (1965.8)",
    "locales": [
      3
    ]
  }
},
{
  "model": "item.album",
  "pk": 5,
  "fields": {
    "album_title": "Rubber Soul (1965.12)",
    "locales": [
      2
    ]
  }
},
{
  "model": "item.album",
  "pk": 6,
  "fields": {
    "album_title": "Revolver (1966.8)",
    "locales": [
      4
    ]
  }
},
{
  "model": "item.album",
  "pk": 7,
  "fields": {
    "album_title": "Sgt. Pepper's Lonely Hearts Club Band (1967.6) ,Magical Mystery Tour (1967.11)[2]",
    "locales": [
      2,
      4
    ]
  }
},
{
  "model": "item.album",
  "pk": 8,
  "fields": {
    "album_title": "The Beatles(aka \ud654\uc774\ud2b8 \uc568\ubc94) (1968.11)",
    "locales": [
      1
    ]
  }
},
{
  "model": "item.album",
  "pk": 9,
  "fields": {
    "album_title": "Yellow Submarine (1969.1)",
    "locales": [
      2,
      4
    ]
  }
},
{
  "model": "item.album",
  "pk": 10,
  "fields": {
    "album_title": "Abbey Road (1969.9)",
    "locales": [
      1
    ]
  }
},
{
  "model": "item.album",
  "pk": 11,
  "fields": {
    "album_title": "Let It Be (1970.5)",
    "locales": [
      4
    ]
  }
},
{
  "model": "item.album",
  "pk": 12,
  "fields": {
    "album_title": "\uc720\uc7ac\ud558 <\uc0ac\ub791\ud558\uae30 \ub54c\ubb38\uc5d0>(1987)",
    "locales": [
      2,
      4
    ]
  }
},
{
  "model": "item.album",
  "pk": 13,
  "fields": {
    "album_title": "\ub4e4\uad6d\ud654 <\ub4e4\uad6d\ud654(1\uc9d1)>(1986)",
    "locales": [
      3
    ]
  }
},
{
  "model": "item.album",
  "pk": 14,
  "fields": {
    "album_title": "\uc2e0\uc911\ud604\uacfc \uc5fd\uc804\ub4e4 <\uc2e0\uc911\ud604\uacfc \uc5fd\uc804\ub4e4>(1974)",
    "locales": [
      4
    ]
  }
},
{
  "model": "item.album",
  "pk": 15,
  "fields": {
    "album_title": "\uae40\ubbfc\uae30 <\uae40\ubbfc\uae30(1\uc9d1)>(1971)",
    "locales": [
      2
    ]
  }
},
{
  "model": "item.album",
  "pk": 16,
  "fields": {
    "album_title": "\uc0b0\uc6b8\ub9bc <\uc544\ub2c8\ubc8c\uc368(1\uc9d1)>(1977)",
    "locales": [
      2
    ]
  }
},
{
  "model": "item.album",
  "pk": 17,
  "fields": {
    "album_title": "\uc5b4\ub5a4\ub0a0 \uff1c\uc5b4\ub5a4\ub0a0 I\uff1e(1986)",
    "locales": [
      4
    ]
  }
},
{
  "model": "item.album",
  "pk": 18,
  "fields": {
    "album_title": "\uc0b0\uc6b8\ub9bc <\uc81c2\uc9d1>(1978)",
    "locales": [
      4
    ]
  }
},
{
  "model": "item.album",
  "pk": 19,
  "fields": {
    "album_title": "\ud55c\ub300\uc218 <\uba40\uace0 \uba3c \uae38(1\uc9d1)>(1974)",
    "locales": [
      1
    ]
  }
},
{
  "model": "item.album",
  "pk": 20,
  "fields": {
    "album_title": "\ub125\uc2a4\ud2b8 \u3008The Return Of N.Ex.T Part 1: The Being\u3009(1994)",
    "locales": [
      2,
      3
    ]
  }
},
{
  "model": "item.album",
  "pk": 21,
  "fields": {
    "album_title": "\uc774\uc0c1\uc740 <\uacf5\ubb34\ub3c4\ud558\uac00>(1995)",
    "locales": [
      3,
      4
    ]
  }
},
{
  "model": "item.album",
  "pk": 22,
  "fields": {
    "album_title": "\uc7a5\ud544\uc21c <\ub098\uc758 \uc678\ub85c\uc6c0\uc774 \ub110 \ubd80\ub97c \ub54c(5\uc9d1)>(1997)",
    "locales": [
      3
    ]
  }
},
{
  "model": "item.album",
  "pk": 23,
  "fields": {
    "album_title": "\uae40\ud604\ucca0 \u3008\uae40\ud604\ucca0 Vol.1\u3009(1989)",
    "locales": [
      3,
      4
    ]
  }
},
{
  "model": "item.album",
  "pk": 24,
  "fields": {
    "album_title": "\uc774\ubb38\uc138 <\uc774\ubb38\uc138 4>(1987)",
    "locales": [
      2,
      3
    ]
  }
},
{
  "model": "item.album",
  "pk": 25,
  "fields": {
    "album_title": "\uc2dc\uc778\uacfc \ucd0c\uc7a5 <\ud478\ub978 \ub3db(2\uc9d1)>(1986)",
    "locales": [
      1
    ]
  }
},
{
  "model": "item.album",
  "pk": 26,
  "fields": {
    "album_title": "\uc0ac\ub791\uacfc \ud3c9\ud654 <\ud55c\ub3d9\uc548 \ub738 \ud588\uc5c8\uc9c0(1\uc9d1)>(1977)",
    "locales": [
      1
    ]
  }
},
{
  "model": "item.album",
  "pk": 27,
  "fields": {
    "album_title": "\uae40\ud604\uc2dd \u3008\uae40\ud604\uc2dd III\u3009(1986)",
    "locales": [
      3,
      4
    ]
  }
},
{
  "model": "item.album",
  "pk": 28,
  "fields": {
    "album_title": "\ud55c\uc601\uc560 <\ubc14\ub77c\ubcf8\ub2e4(2\uc9d1)>(1988)",
    "locales": [
      4
    ]
  }
},
{
  "model": "item.album",
  "pk": 29,
  "fields": {
    "album_title": "\ub378\ub9ac \uc2a4\ud30c\uc774\uc2a4 \u3008Deli Spice\u3009(1997)",
    "locales": [
      2,
      3
    ]
  }
},
{
  "model": "item.album",
  "pk": 30,
  "fields": {
    "album_title": "\ub4c0\uc2a4 \u3008Force Deux\u3009(1995)",
    "locales": [
      3
    ]
  }
},
{
  "model": "item.album",
  "pk": 31,
  "fields": {
    "album_title": "\uc5b4\ub5a4\ub0a0 <\uc5b4\ub5a4\ub0a0 II>(1989)",
    "locales": [
      2
    ]
  }
},
{
  "model": "item.song",
  "pk": 1,
  "fields": {
    "title": "Please Please Me (1963.3) song-1",
    "length": 224,
    "track": 1,
    "album": 1
  }
},
{
  "model": "item.song",
  "pk": 2,
  "fields": {
    "title": "Please Please Me (1963.3) song-2",
    "length": 454,
    "track": 2,
    "album": 1
  }
},
{
  "model": "item.song",
  "pk": 3,
  "fields": {
    "title": "Please Please Me (1963.3) song-3",
    "length": 455,
    "track": 3,
    "album": 1
  }
},
{
  "model": "item.song",
  "pk": 4,
  "fields": {
    "title": "Please Please Me (1963.3) song-4",
    "length": 299,
    "track": 4,
    "album": 1
  }
},
{
  "model": "item.song",
  "pk": 5,
  "fields": {
    "title": "Please Please Me (1963.3) song-5",
    "length": 142,
    "track": 5,
    "album": 1
  }
},
{
  "model": "item.song",
  "pk": 6,
  "fields": {
    "title": "Please Please Me (1963.3) song-6",
    "length": 367,
    "track": 6,
    "album": 1
  }
},
{
  "model": "item.song",
  "pk": 7,
  "fields": {
    "title": "Please Please Me (1963.3) song-7",
    "length": 438,
    "track": 7,
    "album": 1
  }
},
{
  "model": "item.song",
  "pk": 8,
  "fields": {
    "title": "Please Please Me (1963.3) song-8",
    "length": 439,
    "track": 8,
    "album": 1
  }
},
{
  "model": "item.song",
  "pk": 9,
  "fields": {
    "title": "Please Please Me (1963.3) song-9",
    "length": 313,
    "track": 9,
    "album": 1
  }
},
{
  "model": "item.song",
  "pk": 10,
  "fields": {
    "title": "Please Please Me (1963.3) song-10",
    "length": 369,
    "track": 10,
    "album": 1
  }
},
{
  "model": "item.song",
  "pk": 11,
  "fields": {
    "title": "Please Please Me (1963.3) song-11",
    "length": 190,
    "track": 11,
    "album": 1
  }
},
{
  "model": "item.song",
  "pk": 12,
  "fields": {
    "title": "With The Beatles (1963.11) song-1",
    "length": 114,
    "track": 1,
    "album": 2
  }
},
{
  "model": "item.song",
  "pk": 13,
  "fields": {
    "title": "With The Beatles (1963.11) song-2",
    "length": 494,
    "track": 2,
    "album": 2
  }
},
{
  "model": "item.song",
  "pk": 14,
  "fields": {
    "title": "With The Beatles (1963.11) song-3",
    "length": 227,
    "track": 3,
    "album": 2
  }
},
{
  "model": "item.song",
  "pk": 15,
  "fields": {
    "title": "With The Beatles (1963.11) song-4",
    "length": 391,
    "track": 4,
    "album": 2
  }
},
{
  "model": "item.song",
  "pk": 16,
  "fields": {
    "title": "With The Beatles (1963.11) song-5",
    "length": 105,
    "track": 5,
    "album": 2
  }
},
{
  "model": "item.song",
  "pk": 17,
  "fields": {
    "title": "With The Beatles (1963.11) song-6",
    "length": 298,
    "track": 6,
    "album": 2
  }
},
{
  "model": "item.song",
  "pk": 18,
  "fields": {
    "title": "With The Beatles (1963.11) song-7",
    "length": 361,
    "track": 7,
    "album": 2
  }
},
{
  "model": "item.song",
  "pk": 19,
  "fields": {
    "title": "With The Beatles (1963.11) song-8",
    "length": 134,
    "track": 8,
    "album": 2
  }
},
{
  "model": "item.song",
  "pk": 20,
  "fields": {
    "title": "With The Beatles (1963.11) song-9",
    "length": 106,
    "track": 9,
    "album": 2
  }
},
{
  "model": "item.song",
  "pk": 21,
  "fields": {
    "title": "With The Beatles (1963.11) song-10",
    "length": 480,
    "track": 10,
    "album": 2
  }
},
{
  "model": "item.song",
  "pk": 22,
  "fields": {
    "title": "With The Beatles (1963.11) song-11",
    "length": 361,
    "track": 11,
    "album": 2
  }
},
{
  "model": "item.song",
  "pk": 23,
  "fields": {
    "title": "A Hard Day's Night (1964.7), Beatles for Sale (1964.12) song-1",
    "length": 334,
    "track": 1,
    "album": 3
  }
},
{
  "model": "item.song",
  "pk": 24,
  "fields": {
    "title": "A Hard Day's Night (1964.7), Beatles for Sale (1964.12) song-2",
    "length": 241,
    "track": 2,
    "album": 3
  }
},
{
  "model": "item.song",
  "pk": 25,
  "fields": {
    "title": "A Hard Day's Night (1964.7), Beatles for Sale (1964.12) song-3",
    "length": 351,
    "track": 3,
    "album": 3
  }
},
{
  "model": "item.song",
  "pk": 26,
  "fields": {
    "title": "A Hard Day's Night (1964.7), Beatles for Sale (1964.12) song-4",
    "length": 293,
    "track": 4,
    "album": 3
  }
},
{
  "model": "item.song",
  "pk": 27,
  "fields": {
    "title": "A Hard Day's Night (1964.7), Beatles for Sale (1964.12) song-5",
    "length": 475,
    "track": 5,
    "album": 3
  }
},
{
  "model": "item.song",
  "pk": 28,
  "fields": {
    "title": "A Hard Day's Night (1964.7), Beatles for Sale (1964.12) song-6",
    "length": 158,
    "track": 6,
    "album": 3
  }
},
{
  "model": "item.song",
  "pk": 29,
  "fields": {
    "title": "A Hard Day's Night (1964.7), Beatles for Sale (1964.12) song-7",
    "length": 351,
    "track": 7,
    "album": 3
  }
},
{
  "model": "item.song",
  "pk": 30,
  "fields": {
    "title": "A Hard Day's Night (1964.7), Beatles for Sale (1964.12) song-8",
    "length": 256,
    "track": 8,
    "album": 3
  }
},
{
  "model": "item.song",
  "pk": 31,
  "fields": {
    "title": "A Hard Day's Night (1964.7), Beatles for Sale (1964.12) song-9",
    "length": 188,
    "track": 9,
    "album": 3
  }
},
{
  "model": "item.song",
  "pk": 32,
  "fields": {
    "title": "A Hard Day's Night (1964.7), Beatles for Sale (1964.12) song-10",
    "length": 139,
    "track": 10,
    "album": 3
  }
},
{
  "model": "item.song",
  "pk": 33,
  "fields": {
    "title": "A Hard Day's Night (1964.7), Beatles for Sale (1964.12) song-11",
    "length": 284,
    "track": 11,
    "album": 3
  }
},
{
  "model": "item.song",
  "pk": 34,
  "fields": {
    "title": "Help! (1965.8) song-1",
    "length": 218,
    "track": 1,
    "album": 4
  }
},
{
  "model": "item.song",
  "pk": 35,
  "fields": {
    "title": "Help! (1965.8) song-2",
    "length": 474,
    "track": 2,
    "album": 4
  }
},
{
  "model": "item.song",
  "pk": 36,
  "fields": {
    "title": "Help! (1965.8) song-3",
    "length": 249,
    "track": 3,
    "album": 4
  }
},
{
  "model": "item.song",
  "pk": 37,
  "fields": {
    "title": "Help! (1965.8) song-4",
    "length": 252,
    "track": 4,
    "album": 4
  }
},
{
  "model": "item.song",
  "pk": 38,
  "fields": {
    "title": "Help! (1965.8) song-5",
    "length": 399,
    "track": 5,
    "album": 4
  }
},
{
  "model": "item.song",
  "pk": 39,
  "fields": {
    "title": "Help! (1965.8) song-6",
    "length": 116,
    "track": 6,
    "album": 4
  }
},
{
  "model": "item.song",
  "pk": 40,
  "fields": {
    "title": "Help! (1965.8) song-7",
    "length": 229,
    "track": 7,
    "album": 4
  }
},
{
  "model": "item.song",
  "pk": 41,
  "fields": {
    "title": "Help! (1965.8) song-8",
    "length": 253,
    "track": 8,
    "album": 4
  }
},
{
  "model": "item.song",
  "pk": 42,
  "fields": {
    "title": "Help! (1965.8) song-9",
    "length": 359,
    "track": 9,
    "album": 4
  }
},
{
  "model": "item.song",
  "pk": 43,
  "fields": {
    "title": "Help! (1965.8) song-10",
    "length": 361,
    "track": 10,
    "album": 4
  }
},
{
  "model": "item.song",
  "pk": 44,
  "fields": {
    "title": "Help! (1965.8) song-11",
    "length": 423,
    "track": 11,
    "album": 4
  }
},
{
  "model": "item.song",
  "pk": 45,
  "fields": {
    "title": "Rubber Soul (1965.12) song-1",
    "length": 166,
    "track": 1,
    "album": 5
  }
},
{
  "model": "item.song",
  "pk": 46,
  "fields": {
    "title": "Rubber Soul (1965.12) song-2",
    "length": 113,
    "track": 2,
    "album": 5
  }
},
{
  "model": "item.song",
  "pk": 47,
  "fields": {
    "title": "Rubber Soul (1965.12) song-3",
    "length": 377,
    "track": 3,
    "album": 5
  }
},
{
  "model": "item.song",
  "pk": 48,
  "fields": {
    "title": "Rubber Soul (1965.12) song-4",
    "length": 271,
    "track": 4,
    "album": 5
  }
},
{
  "model": "item.song",
  "pk": 49,
  "fields": {
    "title": "Rubber Soul (1965.12) song-5",
    "length": 199,
    "track": 5,
    "album": 5
  }
},
{
  "model": "item.song",
  "pk": 50,
  "fields": {
    "title": "Rubber Soul (1965.12) song-6",
    "length": 500,
    "track": 6,
    "album": 5
  }
},
{
  "model": "item.song",
  "pk": 51,
  "fields": {
    "title": "Rubber Soul (1965.12) song-7",
    "length": 466,
    "track": 7,
    "album": 5
  }
},
{
  "model": "item.song",
  "pk": 52,
  "fields": {
    "title": "Rubber Soul (1965.12) song-8",
    "length": 238,
    "track": 8,
    "album": 5
  }
},
{
  "model": "item.song",
  "pk": 53,
  "fields": {
    "title": "Rubber Soul (1965.12) song-9",
    "length": 128,
    "track": 9,
    "album": 5
  }
},
{
  "model": "item.song",
  "pk": 54,
  "fields": {
    "title": "Rubber Soul (1965.12) song-10",
    "length": 250,
    "track": 10,
    "album": 5
  }
},
{
  "model": "item.song",
  "pk": 55,
  "fields": {
    "title": "Rubber Soul (1965.12) song-11",
    "length": 410,
    "track": 11,
    "album": 5
  }
},
{
  "model": "item.song",
  "pk": 56,
  "fields": {
    "title": "Revolver (1966.8) song-1",
    "length": 237,
    "track": 1,
    "album": 6
  }
},
{
  "model": "item.song",
  "pk": 57,
  "fields": {
    "title": "Revolver (1966.8) song-2",
    "length": 393,
    "track": 2,
    "album": 6
  }
},
{
  "model": "item.song",
  "pk": 58,
  "fields": {
    "title": "Revolver (1966.8) song-3",
    "length": 242,
    "track": 3,
    "album": 6
  }
},
{
  "model": "item.song",
  "pk": 59,
  "fields": {
    "title": "Revolver (1966.8) song-4",
    "length": 403,
    "track": 4,
    "album": 6
  }
},
{
  "model": "item.song",
  "pk": 60,
  "fields": {
    "title": "Revolver (1966.8) song-5",
    "length": 335,
    "track": 5,
    "album": 6
  }
},
{
  "model": "item.song",
  "pk": 61,
  "fields": {
    "title": "Revolver (1966.8) song-6",
    "length": 290,
    "track": 6,
    "album": 6
  }
},
{
  "model": "item.song",
  "pk": 62,
  "fields": {
    "title": "Revolver (1966.8) song-7",
    "length": 377,
    "track": 7,
    "album": 6
  }
},
{
  "model": "item.song",
  "pk": 63,
  "fields": {
    "title": "Revolver (1966.8) song-8",
    "length": 485,
    "track": 8,
    "album": 6
  }
},
{
  "model": "item.song",
  "pk": 64,
  "fields": {
    "title": "Revolver (1966.8) song-9",
    "length": 178,
    "track": 9,
    "album": 6
  }
},
{
  "model": "item.song",
  "pk": 65,
  "fields": {
    "title": "Revolver (1966.8) song-10",
    "length": 399,
    "track": 10,
    "album": 6
  }
},
{
  "model": "item.song",
  "pk": 66,
  "fields": {
    "title": "Revolver (1966.8) song-11",
    "length": 472,
    "track": 11,
    "album": 6
  }
},
{
  "model": "item.song",
  "pk": 67,
  "fields": {
    "title": "Sgt. Pepper's Lonely Hearts Club Band (1967.6) ,Magical Mystery Tour (1967.11)[2] song-1",
    "length": 463,
    "track": 1,
    "album": 7
  }
},
{
  "model": "item.song",
  "pk": 68,
  "fields": {
    "title": "Sgt. Pepper's Lonely Hearts Club Band (1967.6) ,Magical Mystery Tour (1967.11)[2] song-2",
    "length": 160,
    "track": 2,
    "album": 7
  }
},
{
  "model": "item.song",
  "pk": 69,
  "fields": {
    "title": "Sgt. Pepper's Lonely Hearts Club Band (1967.6) ,Magical Mystery Tour (1967.11)[2] song-3",
    "length": 464,
    "track": 3,
    "album": 7
  }
},
{
  "model": "item.song",
  "pk": 70,
  "fields": {
    "title": "Sgt. Pepper's Lonely Hearts Club Band (1967.6) ,Magical Mystery Tour (1967.11)[2] song-4",
    "length": 128,
    "track": 4,
    "album": 7
  }
},
{
  "model": "item.song",
  "pk": 71,
  "fields": {
    "title": "Sgt. Pepper's Lonely Hearts Club Band (1967.6) ,Magical Mystery Tour (1967.11)[2] song-5",
    "length": 425,
    "track": 5,
    "album": 7
  }
},
{
  "model": "item.song",
  "pk": 72,
  "fields": {
    "title": "Sgt. Pepper's Lonely Hearts Club Band (1967.6) ,Magical Mystery Tour (1967.11)[2] song-6",
    "length": 301,
    "track": 6,
    "album": 7
  }
},
{
  "model": "item.song",
  "pk": 73,
  "fields": {
    "title": "Sgt. Pepper's Lonely Hearts Club Band (1967.6) ,Magical Mystery Tour (1967.11)[2] song-7",
    "length": 102,
    "track": 7,
    "album": 7
  }
},
{
  "model": "item.song",
  "pk": 74,
  "fields": {
    "title": "Sgt. Pepper's Lonely Hearts Club Band (1967.6) ,Magical Mystery Tour (1967.11)[2] song-8",
    "length": 329,
    "track": 8,
    "album": 7
  }
},
{
  "model": "item.song",
  "pk": 75,
  "fields": {
    "title": "Sgt. Pepper's Lonely Hearts Club Band (1967.6) ,Magical Mystery Tour (1967.11)[2] song-9",
    "length": 470,
    "track": 9,
    "album": 7
  }
},
{
  "model": "item.song",
  "pk": 76,
  "fields": {
    "title": "Sgt. Pepper's Lonely Hearts Club Band (1967.6) ,Magical Mystery Tour (1967.11)[2] song-10",
    "length": 237,
    "track": 10,
    "album": 7
  }
},
{
  "model": "item.song",
  "pk": 77,
  "fields": {
    "title": "Sgt. Pepper's Lonely Hearts Club Band (1967.6) ,Magical Mystery Tour (1967.11)[2] song-11",
    "length": 150,
    "track": 11,
    "album": 7
  }
},
{
  "model": "item.song",
  "pk": 78,
  "fields": {
    "title": "The Beatles(aka \ud654\uc774\ud2b8 \uc568\ubc94) (1968.11) song-1",
    "length": 207,
    "track": 1,
    "album": 8
  }
},
{
  "model": "item.song",
  "pk": 79,
  "fields": {
    "title": "The Beatles(aka \ud654\uc774\ud2b8 \uc568\ubc94) (1968.11) song-2",
    "length": 165,
    "track": 2,
    "album": 8
  }
},
{
  "model": "item.song",
  "pk": 80,
  "fields": {
    "title": "The Beatles(aka \ud654\uc774\ud2b8 \uc568\ubc94) (1968.11) song-3",
    "length": 303,
    "track": 3,
    "album": 8
  }
},
{
  "model": "item.song",
  "pk": 81,
  "fields": {
    "title": "The Beatles(aka \ud654\uc774\ud2b8 \uc568\ubc94) (1968.11) song-4",
    "length": 230,
    "track": 4,
    "album": 8
  }
},
{
  "model": "item.song",
  "pk": 82,
  "fields": {
    "title": "The Beatles(aka \ud654\uc774\ud2b8 \uc568\ubc94) (1968.11) song-5",
    "length": 340,
    "track": 5,
    "album": 8
  }
},
{
  "model": "item.song",
  "pk": 83,
  "fields": {
    "title": "The Beatles(aka \ud654\uc774\ud2b8 \uc568\ubc94) (1968.11) song-6",
    "length": 147,
    "track": 6,
    "album": 8
  }
},
{
  "model": "item.song",
  "pk": 84,
  "fields": {
    "title": "The Beatles(aka \ud654\uc774\ud2b8 \uc568\ubc94) (1968.11) song-7",
    "length": 237,
    "track": 7,
    "album": 8
  }
},
{
  "model": "item.song",
  "pk": 85,
  "fields": {
    "title": "The Beatles(aka \ud654\uc774\ud2b8 \uc568\ubc94) (1968.11) song-8",
    "length": 227,
    "track": 8,
    "album": 8
  }
},
{
  "model": "item.song",
  "pk": 86,
  "fields": {
    "title": "The Beatles(aka \ud654\uc774\ud2b8 \uc568\ubc94) (1968.11) song-9",
    "length": 231,
    "track": 9,
    "album": 8
  }
},
{
  "model": "item.song",
  "pk": 87,
  "fields": {
    "title": "The Beatles(aka \ud654\uc774\ud2b8 \uc568\ubc94) (1968.11) song-10",
    "length": 498,
    "track": 10,
    "album": 8
  }
},
{
  "model": "item.song",
  "pk": 88,
  "fields": {
    "title": "The Beatles(aka \ud654\uc774\ud2b8 \uc568\ubc94) (1968.11) song-11",
    "length": 406,
    "track": 11,
    "album": 8
  }
},
{
  "model": "item.song",
  "pk": 89,
  "fields": {
    "title": "Yellow Submarine (1969.1) song-1",
    "length": 371,
    "track": 1,
    "album": 9
  }
},
{
  "model": "item.song",
  "pk": 90,
  "fields": {
    "title": "Yellow Submarine (1969.1) song-2",
    "length": 165,
    "track": 2,
    "album": 9
  }
},
{
  "model": "item.song",
  "pk": 91,
  "fields": {
    "title": "Yellow Submarine (1969.1) song-3",
    "length": 270,
    "track": 3,
    "album": 9
  }
},
{
  "model": "item.song",
  "pk": 92,
  "fields": {
    "title": "Yellow Submarine (1969.1) song-4",
    "length": 372,
    "track": 4,
    "album": 9
  }
},
{
  "model": "item.song",
  "pk": 93,
  "fields": {
    "title": "Yellow Submarine (1969.1) song-5",
    "length": 175,
    "track": 5,
    "album": 9
  }
},
{
  "model": "item.song",
  "pk": 94,
  "fields": {
    "title": "Yellow Submarine (1969.1) song-6",
    "length": 184,
    "track": 6,
    "album": 9
  }
},
{
  "model": "item.song",
  "pk": 95,
  "fields": {
    "title": "Yellow Submarine (1969.1) song-7",
    "length": 410,
    "track": 7,
    "album": 9
  }
},
{
  "model": "item.song",
  "pk": 96,
  "fields": {
    "title": "Yellow Submarine (1969.1) song-8",
    "length": 203,
    "track": 8,
    "album": 9
  }
},
{
  "model": "item.song",
  "pk": 97,
  "fields": {
    "title": "Yellow Submarine (1969.1) song-9",
    "length": 491,
    "track": 9,
    "album": 9
  }
},
{
  "model": "item.song",
  "pk": 98,
  "fields": {
    "title": "Yellow Submarine (1969.1) song-10",
    "length": 477,
    "track": 10,
    "album": 9
  }
},
{
  "model": "item.song",
  "pk": 99,
  "fields": {
    "title": "Yellow Submarine (1969.1) song-11",
    "length": 149,
    "track": 11,
    "album": 9
  }
},
{
  "model": "item.song",
  "pk": 100,
  "fields": {
    "title": "Abbey Road (1969.9) song-1",
    "length": 107,
    "track": 1,
    "album": 10
  }
},
{
  "model": "item.song",
  "pk": 101,
  "fields": {
    "title": "Abbey Road (1969.9) song-2",
    "length": 324,
    "track": 2,
    "album": 10
  }
},
{
  "model": "item.song",
  "pk": 102,
  "fields": {
    "title": "Abbey Road (1969.9) song-3",
    "length": 163,
    "track": 3,
    "album": 10
  }
},
{
  "model": "item.song",
  "pk": 103,
  "fields": {
    "title": "Abbey Road (1969.9) song-4",
    "length": 281,
    "track": 4,
    "album": 10
  }
},
{
  "model": "item.song",
  "pk": 104,
  "fields": {
    "title": "Abbey Road (1969.9) song-5",
    "length": 325,
    "track": 5,
    "album": 10
  }
},
{
  "model": "item.song",
  "pk": 105,
  "fields": {
    "title": "Abbey Road (1969.9) song-6",
    "length": 294,
    "track": 6,
    "album": 10
  }
},
{
  "model": "item.song",
  "pk": 106,
  "fields": {
    "title": "Abbey Road (1969.9) song-7",
    "length": 475,
    "track": 7,
    "album": 10
  }
},
{
  "model": "item.song",
  "pk": 107,
  "fields": {
    "title": "Abbey Road (1969.9) song-8",
    "length": 113,
    "track": 8,
    "album": 10
  }
},
{
  "model": "item.song",
  "pk": 108,
  "fields": {
    "title": "Abbey Road (1969.9) song-9",
    "length": 425,
    "track": 9,
    "album": 10
  }
},
{
  "model": "item.song",
  "pk": 109,
  "fields": {
    "title": "Abbey Road (1969.9) song-10",
    "length": 477,
    "track": 10,
    "album": 10
  }
},
{
  "model": "item.song",
  "pk": 110,
  "fields": {
    "title": "Abbey Road (1969.9) song-11",
    "length": 440,
    "track": 11,
    "album": 10
  }
},
{
  "model": "item.song",
  "pk": 111,
  "fields": {
    "title": "Let It Be (1970.5) song-1",
    "length": 489,
    "track": 1,
    "album": 11
  }
},
{
  "model": "item.song",
  "pk": 112,
  "fields": {
    "title": "Let It Be (1970.5) song-2",
    "length": 235,
    "track": 2,
    "album": 11
  }
},
{
  "model": "item.song",
  "pk": 113,
  "fields": {
    "title": "Let It Be (1970.5) song-3",
    "length": 249,
    "track": 3,
    "album": 11
  }
},
{
  "model": "item.song",
  "pk": 114,
  "fields": {
    "title": "Let It Be (1970.5) song-4",
    "length": 356,
    "track": 4,
    "album": 11
  }
},
{
  "model": "item.song",
  "pk": 115,
  "fields": {
    "title": "Let It Be (1970.5) song-5",
    "length": 392,
    "track": 5,
    "album": 11
  }
},
{
  "model": "item.song",
  "pk": 116,
  "fields": {
    "title": "Let It Be (1970.5) song-6",
    "length": 320,
    "track": 6,
    "album": 11
  }
},
{
  "model": "item.song",
  "pk": 117,
  "fields": {
    "title": "Let It Be (1970.5) song-7",
    "length": 110,
    "track": 7,
    "album": 11
  }
},
{
  "model": "item.song",
  "pk": 118,
  "fields": {
    "title": "Let It Be (1970.5) song-8",
    "length": 240,
    "track": 8,
    "album": 11
  }
},
{
  "model": "item.song",
  "pk": 119,
  "fields": {
    "title": "Let It Be (1970.5) song-9",
    "length": 158,
    "track": 9,
    "album": 11
  }
},
{
  "model": "item.song",
  "pk": 120,
  "fields": {
    "title": "Let It Be (1970.5) song-10",
    "length": 357,
    "track": 10,
    "album": 11
  }
},
{
  "model": "item.song",
  "pk": 121,
  "fields": {
    "title": "Let It Be (1970.5) song-11",
    "length": 250,
    "track": 11,
    "album": 11
  }
},
{
  "model": "item.song",
  "pk": 122,
  "fields": {
    "title": "\uc720\uc7ac\ud558 <\uc0ac\ub791\ud558\uae30 \ub54c\ubb38\uc5d0>(1987) song-1",
    "length": 165,
    "track": 1,
    "album": 12
  }
},
{
  "model": "item.song",
  "pk": 123,
  "fields": {
    "title": "\uc720\uc7ac\ud558 <\uc0ac\ub791\ud558\uae30 \ub54c\ubb38\uc5d0>(1987) song-2",
    "length": 356,
    "track": 2,
    "album": 12
  }
},
{
  "model": "item.song",
  "pk": 124,
  "fields": {
    "title": "\uc720\uc7ac\ud558 <\uc0ac\ub791\ud558\uae30 \ub54c\ubb38\uc5d0>(1987) song-3",
    "length": 205,
    "track": 3,
    "album": 12
  }
},
{
  "model": "item.song",
  "pk": 125,
  "fields": {
    "title": "\uc720\uc7ac\ud558 <\uc0ac\ub791\ud558\uae30 \ub54c\ubb38\uc5d0>(1987) song-4",
    "length": 222,
    "track": 4,
    "album": 12
  }
},
{
  "model": "item.song",
  "pk": 126,
  "fields": {
    "title": "\uc720\uc7ac\ud558 <\uc0ac\ub791\ud558\uae30 \ub54c\ubb38\uc5d0>(1987) song-5",
    "length": 138,
    "track": 5,
    "album": 12
  }
},
{
  "model": "item.song",
  "pk": 127,
  "fields": {
    "title": "\uc720\uc7ac\ud558 <\uc0ac\ub791\ud558\uae30 \ub54c\ubb38\uc5d0>(1987) song-6",
    "length": 394,
    "track": 6,
    "album": 12
  }
},
{
  "model": "item.song",
  "pk": 128,
  "fields": {
    "title": "\uc720\uc7ac\ud558 <\uc0ac\ub791\ud558\uae30 \ub54c\ubb38\uc5d0>(1987) song-7",
    "length": 120,
    "track": 7,
    "album": 12
  }
},
{
  "model": "item.song",
  "pk": 129,
  "fields": {
    "title": "\uc720\uc7ac\ud558 <\uc0ac\ub791\ud558\uae30 \ub54c\ubb38\uc5d0>(1987) song-8",
    "length": 490,
    "track": 8,
    "album": 12
  }
},
{
  "model": "item.song",
  "pk": 130,
  "fields": {
    "title": "\uc720\uc7ac\ud558 <\uc0ac\ub791\ud558\uae30 \ub54c\ubb38\uc5d0>(1987) song-9",
    "length": 363,
    "track": 9,
    "album": 12
  }
},
{
  "model": "item.song",
  "pk": 131,
  "fields": {
    "title": "\uc720\uc7ac\ud558 <\uc0ac\ub791\ud558\uae30 \ub54c\ubb38\uc5d0>(1987) song-10",
    "length": 359,
    "track": 10,
    "album": 12
  }
},
{
  "model": "item.song",
  "pk": 132,
  "fields": {
    "title": "\uc720\uc7ac\ud558 <\uc0ac\ub791\ud558\uae30 \ub54c\ubb38\uc5d0>(1987) song-11",
    "length": 430,
    "track": 11,
    "album": 12
  }
},
{
  "model": "item.song",
  "pk": 133,
  "fields": {
    "title": "\ub4e4\uad6d\ud654 <\ub4e4\uad6d\ud654(1\uc9d1)>(1986) song-1",
    "length": 253,
    "track": 1,
    "album": 13
  }
},
{
  "model": "item.song",
  "pk": 134,
  "fields": {
    "title": "\ub4e4\uad6d\ud654 <\ub4e4\uad6d\ud654(1\uc9d1)>(1986) song-2",
    "length": 184,
    "track": 2,
    "album": 13
  }
},
{
  "model": "item.song",
  "pk": 135,
  "fields": {
    "title": "\ub4e4\uad6d\ud654 <\ub4e4\uad6d\ud654(1\uc9d1)>(1986) song-3",
    "length": 391,
    "track": 3,
    "album": 13
  }
},
{
  "model": "item.song",
  "pk": 136,
  "fields": {
    "title": "\ub4e4\uad6d\ud654 <\ub4e4\uad6d\ud654(1\uc9d1)>(1986) song-4",
    "length": 452,
    "track": 4,
    "album": 13
  }
},
{
  "model": "item.song",
  "pk": 137,
  "fields": {
    "title": "\ub4e4\uad6d\ud654 <\ub4e4\uad6d\ud654(1\uc9d1)>(1986) song-5",
    "length": 175,
    "track": 5,
    "album": 13
  }
},
{
  "model": "item.song",
  "pk": 138,
  "fields": {
    "title": "\ub4e4\uad6d\ud654 <\ub4e4\uad6d\ud654(1\uc9d1)>(1986) song-6",
    "length": 425,
    "track": 6,
    "album": 13
  }
},
{
  "model": "item.song",
  "pk": 139,
  "fields": {
    "title": "\ub4e4\uad6d\ud654 <\ub4e4\uad6d\ud654(1\uc9d1)>(1986) song-7",
    "length": 489,
    "track": 7,
    "album": 13
  }
},
{
  "model": "item.song",
  "pk": 140,
  "fields": {
    "title": "\ub4e4\uad6d\ud654 <\ub4e4\uad6d\ud654(1\uc9d1)>(1986) song-8",
    "length": 172,
    "track": 8,
    "album": 13
  }
},
{
  "model": "item.song",
  "pk": 141,
  "fields": {
    "title": "\ub4e4\uad6d\ud654 <\ub4e4\uad6d\ud654(1\uc9d1)>(1986) song-9",
    "length": 233,
    "track": 9,
    "album": 13
  }
},
{
  "model": "item.song",
  "pk": 142,
  "fields": {
    "title": "\ub4e4\uad6d\ud654 <\ub4e4\uad6d\ud654(1\uc9d1)>(1986) song-10",
    "length": 278,
    "track": 10,
    "album": 13
  }
},
{
  "model": "item.song",
  "pk": 143,
  "fields": {
    "title": "\ub4e4\uad6d\ud654 <\ub4e4\uad6d\ud654(1\uc9d1)>(1986) song-11",
    "length": 485,
    "track": 11,
    "album": 13
  }
},
{
  "model": "item.song",
  "pk": 144,
  "fields": {
    "title": "\uc2e0\uc911\ud604\uacfc \uc5fd\uc804\ub4e4 <\uc2e0\uc911\ud604\uacfc \uc5fd\uc804\ub4e4>(1974) song-1",
    "length": 388,
    "track": 1,
    "album": 14
  }
},
{
  "model": "item.song",
  "pk": 145,
  "fields": {
    "title": "\uc2e0\uc911\ud604\uacfc \uc5fd\uc804\ub4e4 <\uc2e0\uc911\ud604\uacfc \uc5fd\uc804\ub4e4>(1974) song-2",
    "length": 243,
    "track": 2,
    "album": 14
  }
},
{
  "model": "item.song",
  "pk": 146,
  "fields": {
    "title": "\uc2e0\uc911\ud604\uacfc \uc5fd\uc804\ub4e4 <\uc2e0\uc911\ud604\uacfc \uc5fd\uc804\ub4e4>(1974) song-3",
    "length": 368,
    "track": 3,
    "album": 14
  }
},
{
  "model": "item.song",
  "pk": 147,
  "fields": {
    "title": "\uc2e0\uc911\ud604\uacfc \uc5fd\uc804\ub4e4 <\uc2e0\uc911\ud604\uacfc \uc5fd\uc804\ub4e4>(1974) song-4",
    "length": 171,
    "track": 4,
    "album": 14
  }
},
{
  "model": "item.song",
  "pk": 148,
  "fields": {
    "title": "\uc2e0\uc911\ud604\uacfc \uc5fd\uc804\ub4e4 <\uc2e0\uc911\ud604\uacfc \uc5fd\uc804\ub4e4>(1974) song-5",
    "length": 338,
    "track": 5,
    "album": 14
  }
},
{
  "model": "item.song",
  "pk": 149,
  "fields": {
    "title": "\uc2e0\uc911\ud604\uacfc \uc5fd\uc804\ub4e4 <\uc2e0\uc911\ud604\uacfc \uc5fd\uc804\ub4e4>(1974) song-6",
    "length": 380,
    "track": 6,
    "album": 14
  }
},
{
  "model": "item.song",
  "pk": 150,
  "fields": {
    "title": "\uc2e0\uc911\ud604\uacfc \uc5fd\uc804\ub4e4 <\uc2e0\uc911\ud604\uacfc \uc5fd\uc804\ub4e4>(1974) song-7",
    "length": 322,
    "track": 7,
    "album": 14
  }
},
{
  "model": "item.song",
  "pk": 151,
  "fields": {
    "title": "\uc2e0\uc911\ud604\uacfc \uc5fd\uc804\ub4e4 <\uc2e0\uc911\ud604\uacfc \uc5fd\uc804\ub4e4>(1974) song-8",
    "length": 321,
    "track": 8,
    "album": 14
  }
},
{
  "model": "item.song",
  "pk": 152,
  "fields": {
    "title": "\uc2e0\uc911\ud604\uacfc \uc5fd\uc804\ub4e4 <\uc2e0\uc911\ud604\uacfc \uc5fd\uc804\ub4e4>(1974) song-9",
    "length": 415,
    "track": 9,
    "album": 14
  }
},
{
  "model": "item.song",
  "pk": 153,
  "fields": {
    "title": "\uc2e0\uc911\ud604\uacfc \uc5fd\uc804\ub4e4 <\uc2e0\uc911\ud604\uacfc \uc5fd\uc804\ub4e4>(1974) song-10",
    "length": 425,
    "track": 10,
    "album": 14
  }
},
{
  "model": "item.song",
  "pk": 154,
  "fields": {
    "title": "\uc2e0\uc911\ud604\uacfc \uc5fd\uc804\ub4e4 <\uc2e0\uc911\ud604\uacfc \uc5fd\uc804\ub4e4>(1974) song-11",
    "length": 276,
    "track": 11,
    "album": 14
  }
},
{
  "model": "item.song",
  "pk": 155,
  "fields": {
    "title": "\uae40\ubbfc\uae30 <\uae40\ubbfc\uae30(1\uc9d1)>(1971) song-1",
    "length": 226,
    "track": 1,
    "album": 15
  }
},
{
  "model": "item.song",
  "pk": 156,
  "fields": {
    "title": "\uae40\ubbfc\uae30 <\uae40\ubbfc\uae30(1\uc9d1)>(1971) song-2",
    "length": 237,
    "track": 2,
    "album": 15
  }
},
{
  "model": "item.song",
  "pk": 157,
  "fields": {
    "title": "\uae40\ubbfc\uae30 <\uae40\ubbfc\uae30(1\uc9d1)>(1971) song-3",
    "length": 353,
    "track": 3,
    "album": 15
  }
},
{
  "model": "item.song",
  "pk": 158,
  "fields": {
    "title": "\uae40\ubbfc\uae30 <\uae40\ubbfc\uae30(1\uc9d1)>(1971) song-4",
    "length": 430,
    "track": 4,
    "album": 15
  }
},
{
  "model": "item.song",
  "pk": 159,
  "fields": {
    "title": "\uae40\ubbfc\uae30 <\uae40\ubbfc\uae30(1\uc9d1)>(1971) song-5",
    "length": 247,
    "track": 5,
    "album": 15
  }
},
{
  "model": "item.song",
  "pk": 160,
  "fields": {
    "title": "\uae40\ubbfc\uae30 <\uae40\ubbfc\uae30(1\uc9d1)>(1971) song-6",
    "length": 183,
    "track": 6,
    "album": 15
  }
},
{
  "model": "item.song",
  "pk": 161,
  "fields": {
    "title": "\uae40\ubbfc\uae30 <\uae40\ubbfc\uae30(1\uc9d1)>(1971) song-7",
    "length": 497,
    "track": 7,
    "album": 15
  }
},
{
  "model": "item.song",
  "pk": 162,
  "fields": {
    "title": "\uae40\ubbfc\uae30 <\uae40\ubbfc\uae30(1\uc9d1)>(1971) song-8",
    "length": 324,
    "track": 8,
    "album": 15
  }
},
{
  "model": "item.song",
  "pk": 163,
  "fields": {
    "title": "\uae40\ubbfc\uae30 <\uae40\ubbfc\uae30(1\uc9d1)>(1971) song-9",
    "length": 312,
    "track": 9,
    "album": 15
  }
},
{
  "model": "item.song",
  "pk": 164,
  "fields": {
    "title": "\uae40\ubbfc\uae30 <\uae40\ubbfc\uae30(1\uc9d1)>(1971) song-10",
    "length": 146,
    "track": 10,
    "album": 15
  }
},
{
  "model": "item.song",
  "pk": 165,
  "fields": {
    "title": "\uae40\ubbfc\uae30 <\uae40\ubbfc\uae30(1\uc9d1)>(1971) song-11",
    "length": 495,
    "track": 11,
    "album": 15
  }
},
{
  "model": "item.song",
  "pk": 166,
  "fields": {
    "title": "\uc0b0\uc6b8\ub9bc <\uc544\ub2c8\ubc8c\uc368(1\uc9d1)>(1977) song-1",
    "length": 200,
    "track": 1,
    "album": 16
  }
},
{
  "model": "item.song",
  "pk": 167,
  "fields": {
    "title": "\uc0b0\uc6b8\ub9bc <\uc544\ub2c8\ubc8c\uc368(1\uc9d1)>(1977) song-2",
    "length": 461,
    "track": 2,
    "album": 16
  }
},
{
  "model": "item.song",
  "pk": 168,
  "fields": {
    "title": "\uc0b0\uc6b8\ub9bc <\uc544\ub2c8\ubc8c\uc368(1\uc9d1)>(1977) song-3",
    "length": 107,
    "track": 3,
    "album": 16
  }
},
{
  "model": "item.song",
  "pk": 169,
  "fields": {
    "title": "\uc0b0\uc6b8\ub9bc <\uc544\ub2c8\ubc8c\uc368(1\uc9d1)>(1977) song-4",
    "length": 361,
    "track": 4,
    "album": 16
  }
},
{
  "model": "item.song",
  "pk": 170,
  "fields": {
    "title": "\uc0b0\uc6b8\ub9bc <\uc544\ub2c8\ubc8c\uc368(1\uc9d1)>(1977) song-5",
    "length": 166,
    "track": 5,
    "album": 16
  }
},
{
  "model": "item.song",
  "pk": 171,
  "fields": {
    "title": "\uc0b0\uc6b8\ub9bc <\uc544\ub2c8\ubc8c\uc368(1\uc9d1)>(1977) song-6",
    "length": 198,
    "track": 6,
    "album": 16
  }
},
{
  "model": "item.song",
  "pk": 172,
  "fields": {
    "title": "\uc0b0\uc6b8\ub9bc <\uc544\ub2c8\ubc8c\uc368(1\uc9d1)>(1977) song-7",
    "length": 282,
    "track": 7,
    "album": 16
  }
},
{
  "model": "item.song",
  "pk": 173,
  "fields": {
    "title": "\uc0b0\uc6b8\ub9bc <\uc544\ub2c8\ubc8c\uc368(1\uc9d1)>(1977) song-8",
    "length": 167,
    "track": 8,
    "album": 16
  }
},
{
  "model": "item.song",
  "pk": 174,
  "fields": {
    "title": "\uc0b0\uc6b8\ub9bc <\uc544\ub2c8\ubc8c\uc368(1\uc9d1)>(1977) song-9",
    "length": 119,
    "track": 9,
    "album": 16
  }
},
{
  "model": "item.song",
  "pk": 175,
  "fields": {
    "title": "\uc0b0\uc6b8\ub9bc <\uc544\ub2c8\ubc8c\uc368(1\uc9d1)>(1977) song-10",
    "length": 305,
    "track": 10,
    "album": 16
  }
},
{
  "model": "item.song",
  "pk": 176,
  "fields": {
    "title": "\uc0b0\uc6b8\ub9bc <\uc544\ub2c8\ubc8c\uc368(1\uc9d1)>(1977) song-11",
    "length": 172,
    "track": 11,
    "album": 16
  }
},
{
  "model": "item.song",
  "pk": 177,
  "fields": {
    "title": "\uc5b4\ub5a4\ub0a0 \uff1c\uc5b4\ub5a4\ub0a0 I\uff1e(1986) song-1",
    "length": 133,
    "track": 1,
    "album": 17
  }
},
{
  "model": "item.song",
  "pk": 178,
  "fields": {
    "title": "\uc5b4\ub5a4\ub0a0 \uff1c\uc5b4\ub5a4\ub0a0 I\uff1e(1986) song-2",
    "length": 337,
    "track": 2,
    "album": 17
  }
},
{
  "model": "item.song",
  "pk": 179,
  "fields": {
    "title": "\uc5b4\ub5a4\ub0a0 \uff1c\uc5b4\ub5a4\ub0a0 I\uff1e(1986) song-3",
    "length": 292,
    "track": 3,
    "album": 17
  }
},
{
  "model": "item.song",
  "pk": 180,
  "fields": {
    "title": "\uc5b4\ub5a4\ub0a0 \uff1c\uc5b4\ub5a4\ub0a0 I\uff1e(1986) song-4",
    "length": 178,
    "track": 4,
    "album": 17
  }
},
{
  "model": "item.song",
  "pk": 181,
  "fields": {
    "title": "\uc5b4\ub5a4\ub0a0 \uff1c\uc5b4\ub5a4\ub0a0 I\uff1e(1986) song-5",
    "length": 472,
    "track": 5,
    "album": 17
  }
},
{
  "model": "item.song",
  "pk": 182,
  "fields": {
    "title": "\uc5b4\ub5a4\ub0a0 \uff1c\uc5b4\ub5a4\ub0a0 I\uff1e(1986) song-6",
    "length": 484,
    "track": 6,
    "album": 17
  }
},
{
  "model": "item.song",
  "pk": 183,
  "fields": {
    "title": "\uc5b4\ub5a4\ub0a0 \uff1c\uc5b4\ub5a4\ub0a0 I\uff1e(1986) song-7",
    "length": 477,
    "track": 7,
    "album": 17
  }
},
{
  "model": "item.song",
  "pk": 184,
  "fields": {
    "title": "\uc5b4\ub5a4\ub0a0 \uff1c\uc5b4\ub5a4\ub0a0 I\uff1e(1986) song-8",
    "length": 152,
    "track": 8,
    "album": 17
  }
},
{
  "model": "item.song",
  "pk": 185,
  "fields": {
    "title": "\uc5b4\ub5a4\ub0a0 \uff1c\uc5b4\ub5a4\ub0a0 I\uff1e(1986) song-9",
    "length": 291,
    "track": 9,
    "album": 17
  }
},
{
  "model": "item.song",
  "pk": 186,
  "fields": {
    "title": "\uc5b4\ub5a4\ub0a0 \uff1c\uc5b4\ub5a4\ub0a0 I\uff1e(1986) song-10",
    "length": 113,
    "track": 10,
    "album": 17
  }
},
{
  "model": "item.song",
  "pk": 187,
  "fields": {
    "title": "\uc5b4\ub5a4\ub0a0 \uff1c\uc5b4\ub5a4\ub0a0 I\uff1e(1986) song-11",
    "length": 278,
    "track": 11,
    "album": 17
  }
},
{
  "model": "item.song",
  "pk": 188,
  "fields": {
    "title": "\uc0b0\uc6b8\ub9bc <\uc81c2\uc9d1>(1978) song-1",
    "length": 212,
    "track": 1,
    "album": 18
  }
},
{
  "model": "item.song",
  "pk": 189,
  "fields": {
    "title": "\uc0b0\uc6b8\ub9bc <\uc81c2\uc9d1>(1978) song-2",
    "length": 483,
    "track": 2,
    "album": 18
  }
},
{
  "model": "item.song",
  "pk": 190,
  "fields": {
    "title": "\uc0b0\uc6b8\ub9bc <\uc81c2\uc9d1>(1978) song-3",
    "length": 499,
    "track": 3,
    "album": 18
  }
},
{
  "model": "item.song",
  "pk": 191,
  "fields": {
    "title": "\uc0b0\uc6b8\ub9bc <\uc81c2\uc9d1>(1978) song-4",
    "length": 151,
    "track": 4,
    "album": 18
  }
},
{
  "model": "item.song",
  "pk": 192,
  "fields": {
    "title": "\uc0b0\uc6b8\ub9bc <\uc81c2\uc9d1>(1978) song-5",
    "length": 358,
    "track": 5,
    "album": 18
  }
},
{
  "model": "item.song",
  "pk": 193,
  "fields": {
    "title": "\uc0b0\uc6b8\ub9bc <\uc81c2\uc9d1>(1978) song-6",
    "length": 141,
    "track": 6,
    "album": 18
  }
},
{
  "model": "item.song",
  "pk": 194,
  "fields": {
    "title": "\uc0b0\uc6b8\ub9bc <\uc81c2\uc9d1>(1978) song-7",
    "length": 197,
    "track": 7,
    "album": 18
  }
},
{
  "model": "item.song",
  "pk": 195,
  "fields": {
    "title": "\uc0b0\uc6b8\ub9bc <\uc81c2\uc9d1>(1978) song-8",
    "length": 444,
    "track": 8,
    "album": 18
  }
},
{
  "model": "item.song",
  "pk": 196,
  "fields": {
    "title": "\uc0b0\uc6b8\ub9bc <\uc81c2\uc9d1>(1978) song-9",
    "length": 194,
    "track": 9,
    "album": 18
  }
},
{
  "model": "item.song",
  "pk": 197,
  "fields": {
    "title": "\uc0b0\uc6b8\ub9bc <\uc81c2\uc9d1>(1978) song-10",
    "length": 141,
    "track": 10,
    "album": 18
  }
},
{
  "model": "item.song",
  "pk": 198,
  "fields": {
    "title": "\uc0b0\uc6b8\ub9bc <\uc81c2\uc9d1>(1978) song-11",
    "length": 118,
    "track": 11,
    "album": 18
  }
},
{
  "model": "item.song",
  "pk": 199,
  "fields": {
    "title": "\ud55c\ub300\uc218 <\uba40\uace0 \uba3c \uae38(1\uc9d1)>(1974) song-1",
    "length": 188,
    "track": 1,
    "album": 19
  }
},
{
  "model": "item.song",
  "pk": 200,
  "fields": {
    "title": "\ud55c\ub300\uc218 <\uba40\uace0 \uba3c \uae38(1\uc9d1)>(1974) song-2",
    "length": 100,
    "track": 2,
    "album": 19
  }
},
{
  "model": "item.song",
  "pk": 201,
  "fields": {
    "title": "\ud55c\ub300\uc218 <\uba40\uace0 \uba3c \uae38(1\uc9d1)>(1974) song-3",
    "length": 299,
    "track": 3,
    "album": 19
  }
},
{
  "model": "item.song",
  "pk": 202,
  "fields": {
    "title": "\ud55c\ub300\uc218 <\uba40\uace0 \uba3c \uae38(1\uc9d1)>(1974) song-4",
    "length": 373,
    "track": 4,
    "album": 19
  }
},
{
  "model": "item.song",
  "pk": 203,
  "fields": {
    "title": "\ud55c\ub300\uc218 <\uba40\uace0 \uba3c \uae38(1\uc9d1)>(1974) song-5",
    "length": 344,
    "track": 5,
    "album": 19
  }
},
{
  "model": "item.song",
  "pk": 204,
  "fields": {
    "title": "\ud55c\ub300\uc218 <\uba40\uace0 \uba3c \uae38(1\uc9d1)>(1974) song-6",
    "length": 131,
    "track": 6,
    "album": 19
  }
},
{
  "model": "item.song",
  "pk": 205,
  "fields": {
    "title": "\ud55c\ub300\uc218 <\uba40\uace0 \uba3c \uae38(1\uc9d1)>(1974) song-7",
    "length": 131,
    "track": 7,
    "album": 19
  }
},
{
  "model": "item.song",
  "pk": 206,
  "fields": {
    "title": "\ud55c\ub300\uc218 <\uba40\uace0 \uba3c \uae38(1\uc9d1)>(1974) song-8",
    "length": 441,
    "track": 8,
    "album": 19
  }
},
{
  "model": "item.song",
  "pk": 207,
  "fields": {
    "title": "\ud55c\ub300\uc218 <\uba40\uace0 \uba3c \uae38(1\uc9d1)>(1974) song-9",
    "length": 370,
    "track": 9,
    "album": 19
  }
},
{
  "model": "item.song",
  "pk": 208,
  "fields": {
    "title": "\ud55c\ub300\uc218 <\uba40\uace0 \uba3c \uae38(1\uc9d1)>(1974) song-10",
    "length": 154,
    "track": 10,
    "album": 19
  }
},
{
  "model": "item.song",
  "pk": 209,
  "fields": {
    "title": "\ud55c\ub300\uc218 <\uba40\uace0 \uba3c \uae38(1\uc9d1)>(1974) song-11",
    "length": 335,
    "track": 11,
    "album": 19
  }
},
{
  "model": "item.song",
  "pk": 210,
  "fields": {
    "title": "\ub125\uc2a4\ud2b8 \u3008The Return Of N.Ex.T Part 1: The Being\u3009(1994) song-1",
    "length": 181,
    "track": 1,
    "album": 20
  }
},
{
  "model": "item.song",
  "pk": 211,
  "fields": {
    "title": "\ub125\uc2a4\ud2b8 \u3008The Return Of N.Ex.T Part 1: The Being\u3009(1994) song-2",
    "length": 294,
    "track": 2,
    "album": 20
  }
},
{
  "model": "item.song",
  "pk": 212,
  "fields": {
    "title": "\ub125\uc2a4\ud2b8 \u3008The Return Of N.Ex.T Part 1: The Being\u3009(1994) song-3",
    "length": 344,
    "track": 3,
    "album": 20
  }
},
{
  "model": "item.song",
  "pk": 213,
  "fields": {
    "title": "\ub125\uc2a4\ud2b8 \u3008The Return Of N.Ex.T Part 1: The Being\u3009(1994) song-4",
    "length": 490,
    "track": 4,
    "album": 20
  }
},
{
  "model": "item.song",
  "pk": 214,
  "fields": {
    "title": "\ub125\uc2a4\ud2b8 \u3008The Return Of N.Ex.T Part 1: The Being\u3009(1994) song-5",
    "length": 358,
    "track": 5,
    "album": 20
  }
},
{
  "model": "item.song",
  "pk": 215,
  "fields": {
    "title": "\ub125\uc2a4\ud2b8 \u3008The Return Of N.Ex.T Part 1: The Being\u3009(1994) song-6",
    "length": 135,
    "track": 6,
    "album": 20
  }
},
{
  "model": "item.song",
  "pk": 216,
  "fields": {
    "title": "\ub125\uc2a4\ud2b8 \u3008The Return Of N.Ex.T Part 1: The Being\u3009(1994) song-7",
    "length": 335,
    "track": 7,
    "album": 20
  }
},
{
  "model": "item.song",
  "pk": 217,
  "fields": {
    "title": "\ub125\uc2a4\ud2b8 \u3008The Return Of N.Ex.T Part 1: The Being\u3009(1994) song-8",
    "length": 492,
    "track": 8,
    "album": 20
  }
},
{
  "model": "item.song",
  "pk": 218,
  "fields": {
    "title": "\ub125\uc2a4\ud2b8 \u3008The Return Of N.Ex.T Part 1: The Being\u3009(1994) song-9",
    "length": 243,
    "track": 9,
    "album": 20
  }
},
{
  "model": "item.song",
  "pk": 219,
  "fields": {
    "title": "\ub125\uc2a4\ud2b8 \u3008The Return Of N.Ex.T Part 1: The Being\u3009(1994) song-10",
    "length": 114,
    "track": 10,
    "album": 20
  }
},
{
  "model": "item.song",
  "pk": 220,
  "fields": {
    "title": "\ub125\uc2a4\ud2b8 \u3008The Return Of N.Ex.T Part 1: The Being\u3009(1994) song-11",
    "length": 177,
    "track": 11,
    "album": 20
  }
},
{
  "model": "item.song",
  "pk": 221,
  "fields": {
    "title": "\uc774\uc0c1\uc740 <\uacf5\ubb34\ub3c4\ud558\uac00>(1995) song-1",
    "length": 462,
    "track": 1,
    "album": 21
  }
},
{
  "model": "item.song",
  "pk": 222,
  "fields": {
    "title": "\uc774\uc0c1\uc740 <\uacf5\ubb34\ub3c4\ud558\uac00>(1995) song-2",
    "length": 296,
    "track": 2,
    "album": 21
  }
},
{
  "model": "item.song",
  "pk": 223,
  "fields": {
    "title": "\uc774\uc0c1\uc740 <\uacf5\ubb34\ub3c4\ud558\uac00>(1995) song-3",
    "length": 423,
    "track": 3,
    "album": 21
  }
},
{
  "model": "item.song",
  "pk": 224,
  "fields": {
    "title": "\uc774\uc0c1\uc740 <\uacf5\ubb34\ub3c4\ud558\uac00>(1995) song-4",
    "length": 354,
    "track": 4,
    "album": 21
  }
},
{
  "model": "item.song",
  "pk": 225,
  "fields": {
    "title": "\uc774\uc0c1\uc740 <\uacf5\ubb34\ub3c4\ud558\uac00>(1995) song-5",
    "length": 429,
    "track": 5,
    "album": 21
  }
},
{
  "model": "item.song",
  "pk": 226,
  "fields": {
    "title": "\uc774\uc0c1\uc740 <\uacf5\ubb34\ub3c4\ud558\uac00>(1995) song-6",
    "length": 172,
    "track": 6,
    "album": 21
  }
},
{
  "model": "item.song",
  "pk": 227,
  "fields": {
    "title": "\uc774\uc0c1\uc740 <\uacf5\ubb34\ub3c4\ud558\uac00>(1995) song-7",
    "length": 326,
    "track": 7,
    "album": 21
  }
},
{
  "model": "item.song",
  "pk": 228,
  "fields": {
    "title": "\uc774\uc0c1\uc740 <\uacf5\ubb34\ub3c4\ud558\uac00>(1995) song-8",
    "length": 228,
    "track": 8,
    "album": 21
  }
},
{
  "model": "item.song",
  "pk": 229,
  "fields": {
    "title": "\uc774\uc0c1\uc740 <\uacf5\ubb34\ub3c4\ud558\uac00>(1995) song-9",
    "length": 168,
    "track": 9,
    "album": 21
  }
},
{
  "model": "item.song",
  "pk": 230,
  "fields": {
    "title": "\uc774\uc0c1\uc740 <\uacf5\ubb34\ub3c4\ud558\uac00>(1995) song-10",
    "length": 482,
    "track": 10,
    "album": 21
  }
},
{
  "model": "item.song",
  "pk": 231,
  "fields": {
    "title": "\uc774\uc0c1\uc740 <\uacf5\ubb34\ub3c4\ud558\uac00>(1995) song-11",
    "length": 352,
    "track": 11,
    "album": 21
  }
},
{
  "model": "item.song",
  "pk": 232,
  "fields": {
    "title": "\uc7a5\ud544\uc21c <\ub098\uc758 \uc678\ub85c\uc6c0\uc774 \ub110 \ubd80\ub97c \ub54c(5\uc9d1)>(1997) song-1",
    "length": 188,
    "track": 1,
    "album": 22
  }
},
{
  "model": "item.song",
  "pk": 233,
  "fields": {
    "title": "\uc7a5\ud544\uc21c <\ub098\uc758 \uc678\ub85c\uc6c0\uc774 \ub110 \ubd80\ub97c \ub54c(5\uc9d1)>(1997) song-2",
    "length": 117,
    "track": 2,
    "album": 22
  }
},
{
  "model": "item.song",
  "pk": 234,
  "fields": {
    "title": "\uc7a5\ud544\uc21c <\ub098\uc758 \uc678\ub85c\uc6c0\uc774 \ub110 \ubd80\ub97c \ub54c(5\uc9d1)>(1997) song-3",
    "length": 433,
    "track": 3,
    "album": 22
  }
},
{
  "model": "item.song",
  "pk": 235,
  "fields": {
    "title": "\uc7a5\ud544\uc21c <\ub098\uc758 \uc678\ub85c\uc6c0\uc774 \ub110 \ubd80\ub97c \ub54c(5\uc9d1)>(1997) song-4",
    "length": 300,
    "track": 4,
    "album": 22
  }
},
{
  "model": "item.song",
  "pk": 236,
  "fields": {
    "title": "\uc7a5\ud544\uc21c <\ub098\uc758 \uc678\ub85c\uc6c0\uc774 \ub110 \ubd80\ub97c \ub54c(5\uc9d1)>(1997) song-5",
    "length": 120,
    "track": 5,
    "album": 22
  }
},
{
  "model": "item.song",
  "pk": 237,
  "fields": {
    "title": "\uc7a5\ud544\uc21c <\ub098\uc758 \uc678\ub85c\uc6c0\uc774 \ub110 \ubd80\ub97c \ub54c(5\uc9d1)>(1997) song-6",
    "length": 330,
    "track": 6,
    "album": 22
  }
},
{
  "model": "item.song",
  "pk": 238,
  "fields": {
    "title": "\uc7a5\ud544\uc21c <\ub098\uc758 \uc678\ub85c\uc6c0\uc774 \ub110 \ubd80\ub97c \ub54c(5\uc9d1)>(1997) song-7",
    "length": 290,
    "track": 7,
    "album": 22
  }
},
{
  "model": "item.song",
  "pk": 239,
  "fields": {
    "title": "\uc7a5\ud544\uc21c <\ub098\uc758 \uc678\ub85c\uc6c0\uc774 \ub110 \ubd80\ub97c \ub54c(5\uc9d1)>(1997) song-8",
    "length": 183,
    "track": 8,
    "album": 22
  }
},
{
  "model": "item.song",
  "pk": 240,
  "fields": {
    "title": "\uc7a5\ud544\uc21c <\ub098\uc758 \uc678\ub85c\uc6c0\uc774 \ub110 \ubd80\ub97c \ub54c(5\uc9d1)>(1997) song-9",
    "length": 395,
    "track": 9,
    "album": 22
  }
},
{
  "model": "item.song",
  "pk": 241,
  "fields": {
    "title": "\uc7a5\ud544\uc21c <\ub098\uc758 \uc678\ub85c\uc6c0\uc774 \ub110 \ubd80\ub97c \ub54c(5\uc9d1)>(1997) song-10",
    "length": 168,
    "track": 10,
    "album": 22
  }
},
{
  "model": "item.song",
  "pk": 242,
  "fields": {
    "title": "\uc7a5\ud544\uc21c <\ub098\uc758 \uc678\ub85c\uc6c0\uc774 \ub110 \ubd80\ub97c \ub54c(5\uc9d1)>(1997) song-11",
    "length": 276,
    "track": 11,
    "album": 22
  }
},
{
  "model": "item.song",
  "pk": 243,
  "fields": {
    "title": "\uae40\ud604\ucca0 \u3008\uae40\ud604\ucca0 Vol.1\u3009(1989) song-1",
    "length": 126,
    "track": 1,
    "album": 23
  }
},
{
  "model": "item.song",
  "pk": 244,
  "fields": {
    "title": "\uae40\ud604\ucca0 \u3008\uae40\ud604\ucca0 Vol.1\u3009(1989) song-2",
    "length": 412,
    "track": 2,
    "album": 23
  }
},
{
  "model": "item.song",
  "pk": 245,
  "fields": {
    "title": "\uae40\ud604\ucca0 \u3008\uae40\ud604\ucca0 Vol.1\u3009(1989) song-3",
    "length": 155,
    "track": 3,
    "album": 23
  }
},
{
  "model": "item.song",
  "pk": 246,
  "fields": {
    "title": "\uae40\ud604\ucca0 \u3008\uae40\ud604\ucca0 Vol.1\u3009(1989) song-4",
    "length": 272,
    "track": 4,
    "album": 23
  }
},
{
  "model": "item.song",
  "pk": 247,
  "fields": {
    "title": "\uae40\ud604\ucca0 \u3008\uae40\ud604\ucca0 Vol.1\u3009(1989) song-5",
    "length": 390,
    "track": 5,
    "album": 23
  }
},
{
  "model": "item.song",
  "pk": 248,
  "fields": {
    "title": "\uae40\ud604\ucca0 \u3008\uae40\ud604\ucca0 Vol.1\u3009(1989) song-6",
    "length": 480,
    "track": 6,
    "album": 23
  }
},
{
  "model": "item.song",
  "pk": 249,
  "fields": {
    "title": "\uae40\ud604\ucca0 \u3008\uae40\ud604\ucca0 Vol.1\u3009(1989) song-7",
    "length": 130,
    "track": 7,
    "album": 23
  }
},
{
  "model": "item.song",
  "pk": 250,
  "fields": {
    "title": "\uae40\ud604\ucca0 \u3008\uae40\ud604\ucca0 Vol.1\u3009(1989) song-8",
    "length": 224,
    "track": 8,
    "album": 23
  }
},
{
  "model": "item.song",
  "pk": 251,
  "fields": {
    "title": "\uae40\ud604\ucca0 \u3008\uae40\ud604\ucca0 Vol.1\u3009(1989) song-9",
    "length": 254,
    "track": 9,
    "album": 23
  }
},
{
  "model": "item.song",
  "pk": 252,
  "fields": {
    "title": "\uae40\ud604\ucca0 \u3008\uae40\ud604\ucca0 Vol.1\u3009(1989) song-10",
    "length": 418,
    "track": 10,
    "album": 23
  }
},
{
  "model": "item.song",
  "pk": 253,
  "fields": {
    "title": "\uae40\ud604\ucca0 \u3008\uae40\ud604\ucca0 Vol.1\u3009(1989) song-11",
    "length": 226,
    "track": 11,
    "album": 23
  }
},
{
  "model": "item.song",
  "pk": 254,
  "fields": {
    "title": "\uc774\ubb38\uc138 <\uc774\ubb38\uc138 4>(1987) song-1",
    "length": 442,
    "track": 1,
    "album": 24
  }
},
{
  "model": "item.song",
  "pk": 255,
  "fields": {
    "title": "\uc774\ubb38\uc138 <\uc774\ubb38\uc138 4>(1987) song-2",
    "length": 492,
    "track": 2,
    "album": 24
  }
},
{
  "model": "item.song",
  "pk": 256,
  "fields": {
    "title": "\uc774\ubb38\uc138 <\uc774\ubb38\uc138 4>(1987) song-3",
    "length": 253,
    "track": 3,
    "album": 24
  }
},
{
  "model": "item.song",
  "pk": 257,
  "fields": {
    "title": "\uc774\ubb38\uc138 <\uc774\ubb38\uc138 4>(1987) song-4",
    "length": 497,
    "track": 4,
    "album": 24
  }
},
{
  "model": "item.song",
  "pk": 258,
  "fields": {
    "title": "\uc774\ubb38\uc138 <\uc774\ubb38\uc138 4>(1987) song-5",
    "length": 468,
    "track": 5,
    "album": 24
  }
},
{
  "model": "item.song",
  "pk": 259,
  "fields": {
    "title": "\uc774\ubb38\uc138 <\uc774\ubb38\uc138 4>(1987) song-6",
    "length": 438,
    "track": 6,
    "album": 24
  }
},
{
  "model": "item.song",
  "pk": 260,
  "fields": {
    "title": "\uc774\ubb38\uc138 <\uc774\ubb38\uc138 4>(1987) song-7",
    "length": 335,
    "track": 7,
    "album": 24
  }
},
{
  "model": "item.song",
  "pk": 261,
  "fields": {
    "title": "\uc774\ubb38\uc138 <\uc774\ubb38\uc138 4>(1987) song-8",
    "length": 198,
    "track": 8,
    "album": 24
  }
},
{
  "model": "item.song",
  "pk": 262,
  "fields": {
    "title": "\uc774\ubb38\uc138 <\uc774\ubb38\uc138 4>(1987) song-9",
    "length": 419,
    "track": 9,
    "album": 24
  }
},
{
  "model": "item.song",
  "pk": 263,
  "fields": {
    "title": "\uc774\ubb38\uc138 <\uc774\ubb38\uc138 4>(1987) song-10",
    "length": 380,
    "track": 10,
    "album": 24
  }
},
{
  "model": "item.song",
  "pk": 264,
  "fields": {
    "title": "\uc774\ubb38\uc138 <\uc774\ubb38\uc138 4>(1987) song-11",
    "length": 486,
    "track": 11,
    "album": 24
  }
},
{
  "model": "item.song",
  "pk": 265,
  "fields": {
    "title": "\uc2dc\uc778\uacfc \ucd0c\uc7a5 <\ud478\ub978 \ub3db(2\uc9d1)>(1986) song-1",
    "length": 402,
    "track": 1,
    "album": 25
  }
},
{
  "model": "item.song",
  "pk": 266,
  "fields": {
    "title": "\uc2dc\uc778\uacfc \ucd0c\uc7a5 <\ud478\ub978 \ub3db(2\uc9d1)>(1986) song-2",
    "length": 407,
    "track": 2,
    "album": 25
  }
},
{
  "model": "item.song",
  "pk": 267,
  "fields": {
    "title": "\uc2dc\uc778\uacfc \ucd0c\uc7a5 <\ud478\ub978 \ub3db(2\uc9d1)>(1986) song-3",
    "length": 210,
    "track": 3,
    "album": 25
  }
},
{
  "model": "item.song",
  "pk": 268,
  "fields": {
    "title": "\uc2dc\uc778\uacfc \ucd0c\uc7a5 <\ud478\ub978 \ub3db(2\uc9d1)>(1986) song-4",
    "length": 331,
    "track": 4,
    "album": 25
  }
},
{
  "model": "item.song",
  "pk": 269,
  "fields": {
    "title": "\uc2dc\uc778\uacfc \ucd0c\uc7a5 <\ud478\ub978 \ub3db(2\uc9d1)>(1986) song-5",
    "length": 188,
    "track": 5,
    "album": 25
  }
},
{
  "model": "item.song",
  "pk": 270,
  "fields": {
    "title": "\uc2dc\uc778\uacfc \ucd0c\uc7a5 <\ud478\ub978 \ub3db(2\uc9d1)>(1986) song-6",
    "length": 480,
    "track": 6,
    "album": 25
  }
},
{
  "model": "item.song",
  "pk": 271,
  "fields": {
    "title": "\uc2dc\uc778\uacfc \ucd0c\uc7a5 <\ud478\ub978 \ub3db(2\uc9d1)>(1986) song-7",
    "length": 204,
    "track": 7,
    "album": 25
  }
},
{
  "model": "item.song",
  "pk": 272,
  "fields": {
    "title": "\uc2dc\uc778\uacfc \ucd0c\uc7a5 <\ud478\ub978 \ub3db(2\uc9d1)>(1986) song-8",
    "length": 321,
    "track": 8,
    "album": 25
  }
},
{
  "model": "item.song",
  "pk": 273,
  "fields": {
    "title": "\uc2dc\uc778\uacfc \ucd0c\uc7a5 <\ud478\ub978 \ub3db(2\uc9d1)>(1986) song-9",
    "length": 120,
    "track": 9,
    "album": 25
  }
},
{
  "model": "item.song",
  "pk": 274,
  "fields": {
    "title": "\uc2dc\uc778\uacfc \ucd0c\uc7a5 <\ud478\ub978 \ub3db(2\uc9d1)>(1986) song-10",
    "length": 198,
    "track": 10,
    "album": 25
  }
},
{
  "model": "item.song",
  "pk": 275,
  "fields": {
    "title": "\uc2dc\uc778\uacfc \ucd0c\uc7a5 <\ud478\ub978 \ub3db(2\uc9d1)>(1986) song-11",
    "length": 460,
    "track": 11,
    "album": 25
  }
},
{
  "model": "item.song",
  "pk": 276,
  "fields": {
    "title": "\uc0ac\ub791\uacfc \ud3c9\ud654 <\ud55c\ub3d9\uc548 \ub738 \ud588\uc5c8\uc9c0(1\uc9d1)>(1977) song-1",
    "length": 431,
    "track": 1,
    "album": 26
  }
},
{
  "model": "item.song",
  "pk": 277,
  "fields": {
    "title": "\uc0ac\ub791\uacfc \ud3c9\ud654 <\ud55c\ub3d9\uc548 \ub738 \ud588\uc5c8\uc9c0(1\uc9d1)>(1977) song-2",
    "length": 202,
    "track": 2,
    "album": 26
  }
},
{
  "model": "item.song",
  "pk": 278,
  "fields": {
    "title": "\uc0ac\ub791\uacfc \ud3c9\ud654 <\ud55c\ub3d9\uc548 \ub738 \ud588\uc5c8\uc9c0(1\uc9d1)>(1977) song-3",
    "length": 257,
    "track": 3,
    "album": 26
  }
},
{
  "model": "item.song",
  "pk": 279,
  "fields": {
    "title": "\uc0ac\ub791\uacfc \ud3c9\ud654 <\ud55c\ub3d9\uc548 \ub738 \ud588\uc5c8\uc9c0(1\uc9d1)>(1977) song-4",
    "length": 483,
    "track": 4,
    "album": 26
  }
},
{
  "model": "item.song",
  "pk": 280,
  "fields": {
    "title": "\uc0ac\ub791\uacfc \ud3c9\ud654 <\ud55c\ub3d9\uc548 \ub738 \ud588\uc5c8\uc9c0(1\uc9d1)>(1977) song-5",
    "length": 478,
    "track": 5,
    "album": 26
  }
},
{
  "model": "item.song",
  "pk": 281,
  "fields": {
    "title": "\uc0ac\ub791\uacfc \ud3c9\ud654 <\ud55c\ub3d9\uc548 \ub738 \ud588\uc5c8\uc9c0(1\uc9d1)>(1977) song-6",
    "length": 441,
    "track": 6,
    "album": 26
  }
},
{
  "model": "item.song",
  "pk": 282,
  "fields": {
    "title": "\uc0ac\ub791\uacfc \ud3c9\ud654 <\ud55c\ub3d9\uc548 \ub738 \ud588\uc5c8\uc9c0(1\uc9d1)>(1977) song-7",
    "length": 319,
    "track": 7,
    "album": 26
  }
},
{
  "model": "item.song",
  "pk": 283,
  "fields": {
    "title": "\uc0ac\ub791\uacfc \ud3c9\ud654 <\ud55c\ub3d9\uc548 \ub738 \ud588\uc5c8\uc9c0(1\uc9d1)>(1977) song-8",
    "length": 133,
    "track": 8,
    "album": 26
  }
},
{
  "model": "item.song",
  "pk": 284,
  "fields": {
    "title": "\uc0ac\ub791\uacfc \ud3c9\ud654 <\ud55c\ub3d9\uc548 \ub738 \ud588\uc5c8\uc9c0(1\uc9d1)>(1977) song-9",
    "length": 157,
    "track": 9,
    "album": 26
  }
},
{
  "model": "item.song",
  "pk": 285,
  "fields": {
    "title": "\uc0ac\ub791\uacfc \ud3c9\ud654 <\ud55c\ub3d9\uc548 \ub738 \ud588\uc5c8\uc9c0(1\uc9d1)>(1977) song-10",
    "length": 249,
    "track": 10,
    "album": 26
  }
},
{
  "model": "item.song",
  "pk": 286,
  "fields": {
    "title": "\uc0ac\ub791\uacfc \ud3c9\ud654 <\ud55c\ub3d9\uc548 \ub738 \ud588\uc5c8\uc9c0(1\uc9d1)>(1977) song-11",
    "length": 324,
    "track": 11,
    "album": 26
  }
},
{
  "model": "item.song",
  "pk": 287,
  "fields": {
    "title": "\uae40\ud604\uc2dd \u3008\uae40\ud604\uc2dd III\u3009(1986) song-1",
    "length": 408,
    "track": 1,
    "album": 27
  }
},
{
  "model": "item.song",
  "pk": 288,
  "fields": {
    "title": "\uae40\ud604\uc2dd \u3008\uae40\ud604\uc2dd III\u3009(1986) song-2",
    "length": 220,
    "track": 2,
    "album": 27
  }
},
{
  "model": "item.song",
  "pk": 289,
  "fields": {
    "title": "\uae40\ud604\uc2dd \u3008\uae40\ud604\uc2dd III\u3009(1986) song-3",
    "length": 203,
    "track": 3,
    "album": 27
  }
},
{
  "model": "item.song",
  "pk": 290,
  "fields": {
    "title": "\uae40\ud604\uc2dd \u3008\uae40\ud604\uc2dd III\u3009(1986) song-4",
    "length": 423,
    "track": 4,
    "album": 27
  }
},
{
  "model": "item.song",
  "pk": 291,
  "fields": {
    "title": "\uae40\ud604\uc2dd \u3008\uae40\ud604\uc2dd III\u3009(1986) song-5",
    "length": 209,
    "track": 5,
    "album": 27
  }
},
{
  "model": "item.song",
  "pk": 292,
  "fields": {
    "title": "\uae40\ud604\uc2dd \u3008\uae40\ud604\uc2dd III\u3009(1986) song-6",
    "length": 228,
    "track": 6,
    "album": 27
  }
},
{
  "model": "item.song",
  "pk": 293,
  "fields": {
    "title": "\uae40\ud604\uc2dd \u3008\uae40\ud604\uc2dd III\u3009(1986) song-7",
    "length": 167,
    "track": 7,
    "album": 27
  }
},
{
  "model": "item.song",
  "pk": 294,
  "fields": {
    "title": "\uae40\ud604\uc2dd \u3008\uae40\ud604\uc2dd III\u3009(1986) song-8",
    "length": 319,
    "track": 8,
    "album": 27
  }
},
{
  "model": "item.song",
  "pk": 295,
  "fields": {
    "title": "\uae40\ud604\uc2dd \u3008\uae40\ud604\uc2dd III\u3009(1986) song-9",
    "length": 108,
    "track": 9,
    "album": 27
  }
},
{
  "model": "item.song",
  "pk": 296,
  "fields": {
    "title": "\uae40\ud604\uc2dd \u3008\uae40\ud604\uc2dd III\u3009(1986) song-10",
    "length": 330,
    "track": 10,
    "album": 27
  }
},
{
  "model": "item.song",
  "pk": 297,
  "fields": {
    "title": "\uae40\ud604\uc2dd \u3008\uae40\ud604\uc2dd III\u3009(1986) song-11",
    "length": 303,
    "track": 11,
    "album": 27
  }
},
{
  "model": "item.song",
  "pk": 298,
  "fields": {
    "title": "\ud55c\uc601\uc560 <\ubc14\ub77c\ubcf8\ub2e4(2\uc9d1)>(1988) song-1",
    "length": 334,
    "track": 1,
    "album": 28
  }
},
{
  "model": "item.song",
  "pk": 299,
  "fields": {
    "title": "\ud55c\uc601\uc560 <\ubc14\ub77c\ubcf8\ub2e4(2\uc9d1)>(1988) song-2",
    "length": 149,
    "track": 2,
    "album": 28
  }
},
{
  "model": "item.song",
  "pk": 300,
  "fields": {
    "title": "\ud55c\uc601\uc560 <\ubc14\ub77c\ubcf8\ub2e4(2\uc9d1)>(1988) song-3",
    "length": 396,
    "track": 3,
    "album": 28
  }
},
{
  "model": "item.song",
  "pk": 301,
  "fields": {
    "title": "\ud55c\uc601\uc560 <\ubc14\ub77c\ubcf8\ub2e4(2\uc9d1)>(1988) song-4",
    "length": 311,
    "track": 4,
    "album": 28
  }
},
{
  "model": "item.song",
  "pk": 302,
  "fields": {
    "title": "\ud55c\uc601\uc560 <\ubc14\ub77c\ubcf8\ub2e4(2\uc9d1)>(1988) song-5",
    "length": 324,
    "track": 5,
    "album": 28
  }
},
{
  "model": "item.song",
  "pk": 303,
  "fields": {
    "title": "\ud55c\uc601\uc560 <\ubc14\ub77c\ubcf8\ub2e4(2\uc9d1)>(1988) song-6",
    "length": 494,
    "track": 6,
    "album": 28
  }
},
{
  "model": "item.song",
  "pk": 304,
  "fields": {
    "title": "\ud55c\uc601\uc560 <\ubc14\ub77c\ubcf8\ub2e4(2\uc9d1)>(1988) song-7",
    "length": 405,
    "track": 7,
    "album": 28
  }
},
{
  "model": "item.song",
  "pk": 305,
  "fields": {
    "title": "\ud55c\uc601\uc560 <\ubc14\ub77c\ubcf8\ub2e4(2\uc9d1)>(1988) song-8",
    "length": 307,
    "track": 8,
    "album": 28
  }
},
{
  "model": "item.song",
  "pk": 306,
  "fields": {
    "title": "\ud55c\uc601\uc560 <\ubc14\ub77c\ubcf8\ub2e4(2\uc9d1)>(1988) song-9",
    "length": 267,
    "track": 9,
    "album": 28
  }
},
{
  "model": "item.song",
  "pk": 307,
  "fields": {
    "title": "\ud55c\uc601\uc560 <\ubc14\ub77c\ubcf8\ub2e4(2\uc9d1)>(1988) song-10",
    "length": 423,
    "track": 10,
    "album": 28
  }
},
{
  "model": "item.song",
  "pk": 308,
  "fields": {
    "title": "\ud55c\uc601\uc560 <\ubc14\ub77c\ubcf8\ub2e4(2\uc9d1)>(1988) song-11",
    "length": 120,
    "track": 11,
    "album": 28
  }
},
{
  "model": "item.song",
  "pk": 309,
  "fields": {
    "title": "\ub378\ub9ac \uc2a4\ud30c\uc774\uc2a4 \u3008Deli Spice\u3009(1997) song-1",
    "length": 456,
    "track": 1,
    "album": 29
  }
},
{
  "model": "item.song",
  "pk": 310,
  "fields": {
    "title": "\ub378\ub9ac \uc2a4\ud30c\uc774\uc2a4 \u3008Deli Spice\u3009(1997) song-2",
    "length": 333,
    "track": 2,
    "album": 29
  }
},
{
  "model": "item.song",
  "pk": 311,
  "fields": {
    "title": "\ub378\ub9ac \uc2a4\ud30c\uc774\uc2a4 \u3008Deli Spice\u3009(1997) song-3",
    "length": 274,
    "track": 3,
    "album": 29
  }
},
{
  "model": "item.song",
  "pk": 312,
  "fields": {
    "title": "\ub378\ub9ac \uc2a4\ud30c\uc774\uc2a4 \u3008Deli Spice\u3009(1997) song-4",
    "length": 386,
    "track": 4,
    "album": 29
  }
},
{
  "model": "item.song",
  "pk": 313,
  "fields": {
    "title": "\ub378\ub9ac \uc2a4\ud30c\uc774\uc2a4 \u3008Deli Spice\u3009(1997) song-5",
    "length": 238,
    "track": 5,
    "album": 29
  }
},
{
  "model": "item.song",
  "pk": 314,
  "fields": {
    "title": "\ub378\ub9ac \uc2a4\ud30c\uc774\uc2a4 \u3008Deli Spice\u3009(1997) song-6",
    "length": 331,
    "track": 6,
    "album": 29
  }
},
{
  "model": "item.song",
  "pk": 315,
  "fields": {
    "title": "\ub378\ub9ac \uc2a4\ud30c\uc774\uc2a4 \u3008Deli Spice\u3009(1997) song-7",
    "length": 195,
    "track": 7,
    "album": 29
  }
},
{
  "model": "item.song",
  "pk": 316,
  "fields": {
    "title": "\ub378\ub9ac \uc2a4\ud30c\uc774\uc2a4 \u3008Deli Spice\u3009(1997) song-8",
    "length": 250,
    "track": 8,
    "album": 29
  }
},
{
  "model": "item.song",
  "pk": 317,
  "fields": {
    "title": "\ub378\ub9ac \uc2a4\ud30c\uc774\uc2a4 \u3008Deli Spice\u3009(1997) song-9",
    "length": 174,
    "track": 9,
    "album": 29
  }
},
{
  "model": "item.song",
  "pk": 318,
  "fields": {
    "title": "\ub378\ub9ac \uc2a4\ud30c\uc774\uc2a4 \u3008Deli Spice\u3009(1997) song-10",
    "length": 302,
    "track": 10,
    "album": 29
  }
},
{
  "model": "item.song",
  "pk": 319,
  "fields": {
    "title": "\ub378\ub9ac \uc2a4\ud30c\uc774\uc2a4 \u3008Deli Spice\u3009(1997) song-11",
    "length": 489,
    "track": 11,
    "album": 29
  }
},
{
  "model": "item.song",
  "pk": 320,
  "fields": {
    "title": "\ub4c0\uc2a4 \u3008Force Deux\u3009(1995) song-1",
    "length": 293,
    "track": 1,
    "album": 30
  }
},
{
  "model": "item.song",
  "pk": 321,
  "fields": {
    "title": "\ub4c0\uc2a4 \u3008Force Deux\u3009(1995) song-2",
    "length": 312,
    "track": 2,
    "album": 30
  }
},
{
  "model": "item.song",
  "pk": 322,
  "fields": {
    "title": "\ub4c0\uc2a4 \u3008Force Deux\u3009(1995) song-3",
    "length": 341,
    "track": 3,
    "album": 30
  }
},
{
  "model": "item.song",
  "pk": 323,
  "fields": {
    "title": "\ub4c0\uc2a4 \u3008Force Deux\u3009(1995) song-4",
    "length": 409,
    "track": 4,
    "album": 30
  }
},
{
  "model": "item.song",
  "pk": 324,
  "fields": {
    "title": "\ub4c0\uc2a4 \u3008Force Deux\u3009(1995) song-5",
    "length": 399,
    "track": 5,
    "album": 30
  }
},
{
  "model": "item.song",
  "pk": 325,
  "fields": {
    "title": "\ub4c0\uc2a4 \u3008Force Deux\u3009(1995) song-6",
    "length": 151,
    "track": 6,
    "album": 30
  }
},
{
  "model": "item.song",
  "pk": 326,
  "fields": {
    "title": "\ub4c0\uc2a4 \u3008Force Deux\u3009(1995) song-7",
    "length": 486,
    "track": 7,
    "album": 30
  }
},
{
  "model": "item.song",
  "pk": 327,
  "fields": {
    "title": "\ub4c0\uc2a4 \u3008Force Deux\u3009(1995) song-8",
    "length": 267,
    "track": 8,
    "album": 30
  }
},
{
  "model": "item.song",
  "pk": 328,
  "fields": {
    "title": "\ub4c0\uc2a4 \u3008Force Deux\u3009(1995) song-9",
    "length": 460,
    "track": 9,
    "album": 30
  }
},
{
  "model": "item.song",
  "pk": 329,
  "fields": {
    "title": "\ub4c0\uc2a4 \u3008Force Deux\u3009(1995) song-10",
    "length": 347,
    "track": 10,
    "album": 30
  }
},
{
  "model": "item.song",
  "pk": 330,
  "fields": {
    "title": "\ub4c0\uc2a4 \u3008Force Deux\u3009(1995) song-11",
    "length": 389,
    "track": 11,
    "album": 30
  }
},
{
  "model": "item.song",
  "pk": 331,
  "fields": {
    "title": "\uc5b4\ub5a4\ub0a0 <\uc5b4\ub5a4\ub0a0 II>(1989) song-1",
    "length": 388,
    "track": 1,
    "album": 31
  }
},
{
  "model": "item.song",
  "pk": 332,
  "fields": {
    "title": "\uc5b4\ub5a4\ub0a0 <\uc5b4\ub5a4\ub0a0 II>(1989) song-2",
    "length": 126,
    "track": 2,
    "album": 31
  }
},
{
  "model": "item.song",
  "pk": 333,
  "fields": {
    "title": "\uc5b4\ub5a4\ub0a0 <\uc5b4\ub5a4\ub0a0 II>(1989) song-3",
    "length": 495,
    "track": 3,
    "album": 31
  }
},
{
  "model": "item.song",
  "pk": 334,
  "fields": {
    "title": "\uc5b4\ub5a4\ub0a0 <\uc5b4\ub5a4\ub0a0 II>(1989) song-4",
    "length": 453,
    "track": 4,
    "album": 31
  }
},
{
  "model": "item.song",
  "pk": 335,
  "fields": {
    "title": "\uc5b4\ub5a4\ub0a0 <\uc5b4\ub5a4\ub0a0 II>(1989) song-5",
    "length": 166,
    "track": 5,
    "album": 31
  }
},
{
  "model": "item.song",
  "pk": 336,
  "fields": {
    "title": "\uc5b4\ub5a4\ub0a0 <\uc5b4\ub5a4\ub0a0 II>(1989) song-6",
    "length": 442,
    "track": 6,
    "album": 31
  }
},
{
  "model": "item.song",
  "pk": 337,
  "fields": {
    "title": "\uc5b4\ub5a4\ub0a0 <\uc5b4\ub5a4\ub0a0 II>(1989) song-7",
    "length": 226,
    "track": 7,
    "album": 31
  }
},
{
  "model": "item.song",
  "pk": 338,
  "fields": {
    "title": "\uc5b4\ub5a4\ub0a0 <\uc5b4\ub5a4\ub0a0 II>(1989) song-8",
    "length": 142,
    "track": 8,
    "album": 31
  }
},
{
  "model": "item.song",
  "pk": 339,
  "fields": {
    "title": "\uc5b4\ub5a4\ub0a0 <\uc5b4\ub5a4\ub0a0 II>(1989) song-9",
    "length": 498,
    "track": 9,
    "album": 31
  }
},
{
  "model": "item.song",
  "pk": 340,
  "fields": {
    "title": "\uc5b4\ub5a4\ub0a0 <\uc5b4\ub5a4\ub0a0 II>(1989) song-10",
    "length": 204,
    "track": 10,
    "album": 31
  }
},
{
  "model": "item.song",
  "pk": 341,
  "fields": {
    "title": "\uc5b4\ub5a4\ub0a0 <\uc5b4\ub5a4\ub0a0 II>(1989) song-11",
    "length": 308,
    "track": 11,
    "album": 31
  }
}
]
